[{"commonName":"Abu Musa","countryCode":"IR","countryName":"Iran","stateCode":"22","coords":["26.05474000","55.16243000"]},{"commonName":"Abumusa ","countryCode":"IR","countryName":"Iran","stateCode":"22","coords":["27.19805600","54.36861100"]},{"commonName":"Bandar Abbas","countryCode":"IR","countryName":"Iran","stateCode":"22","coords":["27.18650000","56.28080000"]},{"commonName":"Bandar Charak","countryCode":"IR","countryName":"Iran","stateCode":"22","coords":["26.73055600","54.27472200"]},{"commonName":"Bandar Khamir","countryCode":"IR","countryName":"Iran","stateCode":"22","coords":["26.95185270","55.57268840"]},{"commonName":"Bandar Kong","countryCode":"IR","countryName":"Iran","stateCode":"22","coords":["26.60285650","54.92980580"]},{"commonName":"Bandar Lengeh","countryCode":"IR","countryName":"Iran","stateCode":"22","coords":["26.55792000","54.88067000"]},{"commonName":"Bandar-e-Jask","countryCode":"IR","countryName":"Iran","stateCode":"22","coords":["25.65385140","57.76995600"]},{"commonName":"Bashagard","countryCode":"IR","countryName":"Iran","stateCode":"22","coords":["26.45000000","58.08333000"]},{"commonName":"Bastak","countryCode":"IR","countryName":"Iran","stateCode":"22","coords":["27.20000000","54.36667000"]},{"commonName":"Bikah","countryCode":"IR","countryName":"Iran","stateCode":"22","coords":["27.35404360","57.16993320"]},{"commonName":"Dargahan","countryCode":"IR","countryName":"Iran","stateCode":"22","coords":["26.95833690","56.04316930"]},{"commonName":"Dashti","countryCode":"IR","countryName":"Iran","stateCode":"22","coords":["27.17918870","52.99824000"]},{"commonName":"Dehbārez","countryCode":"IR","countryName":"Iran","stateCode":"22","coords":["27.44841050","57.16675690"]},{"commonName":"Fareghan","countryCode":"IR","countryName":"Iran","stateCode":"22","coords":["28.00785210","56.24459260"]},{"commonName":"Fin","countryCode":"IR","countryName":"Iran","stateCode":"22","coords":["27.63285790","55.88187210"]},{"commonName":"Gerouk","countryCode":"IR","countryName":"Iran","stateCode":"22","coords":["26.58856490","57.08517550"]},{"commonName":"Gouharan","countryCode":"IR","countryName":"Iran","stateCode":"22","coords":["26.59615360","57.88707010"]},{"commonName":"Haji Abad","countryCode":"IR","countryName":"Iran","stateCode":"22","coords":["28.31352140","55.89620570"]},{"commonName":"Hajjiabad","countryCode":"IR","countryName":"Iran","stateCode":"22","coords":["28.33333000","55.83333000"]},{"commonName":"Hasht Bandi","countryCode":"IR","countryName":"Iran","stateCode":"22","coords":["27.14586240","57.43326510"]},{"commonName":"Hormuz","countryCode":"IR","countryName":"Iran","stateCode":"22","coords":["27.09500000","56.45277800"]},{"commonName":"Janah","countryCode":"IR","countryName":"Iran","stateCode":"22","coords":["27.02755080","54.27128050"]},{"commonName":"Jask","countryCode":"IR","countryName":"Iran","stateCode":"22","coords":["25.88333000","58.20000000"]},{"commonName":"Khamir","countryCode":"IR","countryName":"Iran","stateCode":"22","coords":["27.26667000","55.55000000"]},{"commonName":"Kish","countryCode":"IR","countryName":"Iran","stateCode":"22","coords":["26.55778000","54.01944000"]},{"commonName":"Koshkonar","countryCode":"IR","countryName":"Iran","stateCode":"22","coords":["27.25012720","52.85715580"]},{"commonName":"Kouhestak","countryCode":"IR","countryName":"Iran","stateCode":"22","coords":["26.80426850","57.01887130"]},{"commonName":"Lemazan","countryCode":"IR","countryName":"Iran","stateCode":"22","coords":["27.05369130","54.83641080"]},{"commonName":"Minab","countryCode":"IR","countryName":"Iran","stateCode":"22","coords":["27.13104000","57.08716000"]},{"commonName":"Parsian","countryCode":"IR","countryName":"Iran","stateCode":"22","coords":["27.16667000","53.26667000"]},{"commonName":"Qaleh Qazi","countryCode":"IR","countryName":"Iran","stateCode":"22","coords":["27.44472200","56.54777800"]},{"commonName":"Qeshm","countryCode":"IR","countryName":"Iran","stateCode":"22","coords":["26.78333000","55.86667000"]},{"commonName":"Rudan","countryCode":"IR","countryName":"Iran","stateCode":"22","coords":["27.53333000","57.11667000"]},{"commonName":"Ruydar","countryCode":"IR","countryName":"Iran","stateCode":"22","coords":["27.46003100","55.40825820"]},{"commonName":"Sardasht Bashagard","countryCode":"IR","countryName":"Iran","stateCode":"22","coords":["26.45871900","57.88425900"]},{"commonName":"Sargaz","countryCode":"IR","countryName":"Iran","stateCode":"22","coords":["28.42563000","55.70177000"]},{"commonName":"Senderk","countryCode":"IR","countryName":"Iran","stateCode":"22","coords":["26.83816290","57.41788730"]},{"commonName":"Sirik","countryCode":"IR","countryName":"Iran","stateCode":"22","coords":["26.50000000","57.18333000"]},{"commonName":"Suzā","countryCode":"IR","countryName":"Iran","stateCode":"22","coords":["26.77724030","56.04379160"]},{"commonName":"Takht","countryCode":"IR","countryName":"Iran","stateCode":"22","coords":["27.50356930","56.62731160"]},{"commonName":"Tazian","countryCode":"IR","countryName":"Iran","stateCode":"22","coords":["27.29016000","56.15210300"]},{"commonName":"Tirour","countryCode":"IR","countryName":"Iran","stateCode":"22","coords":["27.33793880","56.95310350"]},{"commonName":"Ziyārat Ali","countryCode":"IR","countryName":"Iran","stateCode":"22","coords":["27.73557730","57.21072420"]}]