[{"commonName":"Būgai","countryCode":"LT","countryName":"Lithuania","stateCode":"TA","coords":["55.41387000","22.60894000"]},{"commonName":"Jurbarkas","countryCode":"LT","countryName":"Lithuania","stateCode":"TA","coords":["55.10859000","22.79885000"]},{"commonName":"Pagėgiai","countryCode":"LT","countryName":"Lithuania","stateCode":"TA","coords":["55.13400000","21.90446000"]},{"commonName":"Šilalė","countryCode":"LT","countryName":"Lithuania","stateCode":"TA","coords":["55.46667000","22.20000000"]},{"commonName":"Taurage","countryCode":"LT","countryName":"Lithuania","stateCode":"TA","coords":["55.25222000","22.28972000"]}]