[{"commonName":"Hải Dương","countryCode":"VN","countryName":"Vietnam","stateCode":"61","coords":["20.94099000","106.33302000"]},{"commonName":"Huyện Bình Giang","countryCode":"VN","countryName":"Vietnam","stateCode":"61","coords":["20.87586000","106.19138000"]},{"commonName":"Huyện Cẩm Giàng","countryCode":"VN","countryName":"Vietnam","stateCode":"61","coords":["20.95000000","106.21667000"]},{"commonName":"Huyện Gia Lộc","countryCode":"VN","countryName":"Vietnam","stateCode":"61","coords":["20.85164000","106.29130000"]},{"commonName":"Huyện Kinh Môn","countryCode":"VN","countryName":"Vietnam","stateCode":"61","coords":["21.01634000","106.50384000"]},{"commonName":"Huyện Nam Sách","countryCode":"VN","countryName":"Vietnam","stateCode":"61","coords":["21.00484000","106.34042000"]},{"commonName":"Huyện Thanh Miện","countryCode":"VN","countryName":"Vietnam","stateCode":"61","coords":["20.77953000","106.22218000"]},{"commonName":"Thị Xã Chí Linh","countryCode":"VN","countryName":"Vietnam","stateCode":"61","coords":["21.13722000","106.39638000"]}]