[{"commonName":"Biakoye","countryCode":"GH","countryName":"Ghana","stateCode":"OT","coords":["7.11698690","0.32324300"]},{"commonName":"Jasikan","countryCode":"GH","countryName":"Ghana","stateCode":"OT","coords":["7.40940880","0.44301500"]},{"commonName":"Kadjebi","countryCode":"GH","countryName":"Ghana","stateCode":"OT","coords":["7.52631920","0.46704770"]},{"commonName":"Krachi East","countryCode":"GH","countryName":"Ghana","stateCode":"OT","coords":["7.77196980","-0.07763760"]},{"commonName":"Krachi Nchumuru","countryCode":"GH","countryName":"Ghana","stateCode":"OT","coords":["8.14849800","-0.16349880"]},{"commonName":"Krachi West","countryCode":"GH","countryName":"Ghana","stateCode":"OT","coords":["7.98282160","-0.34886270"]},{"commonName":"Nkwanta North","countryCode":"GH","countryName":"Ghana","stateCode":"OT","coords":["8.35180760","0.12217620"]},{"commonName":"Nkwanta South","countryCode":"GH","countryName":"Ghana","stateCode":"OT","coords":["8.25931340","0.50185190"]}]