[{"commonName":"Anse à Galets","countryCode":"HT","countryName":"Haiti","stateCode":"OU","coords":["18.83449000","-72.86644000"]},{"commonName":"Arcahaie","countryCode":"HT","countryName":"Haiti","stateCode":"OU","coords":["18.83333000","-72.41667000"]},{"commonName":"Arrondissement de Croix des Bouquets","countryCode":"HT","countryName":"Haiti","stateCode":"OU","coords":["18.48333000","-72.01667000"]},{"commonName":"Arrondissement de Léogâne","countryCode":"HT","countryName":"Haiti","stateCode":"OU","coords":["18.41667000","-72.75000000"]},{"commonName":"Arrondissement de Port-au-Prince","countryCode":"HT","countryName":"Haiti","stateCode":"OU","coords":["18.50000000","-72.36667000"]},{"commonName":"Cabaret","countryCode":"HT","countryName":"Haiti","stateCode":"OU","coords":["18.73582000","-72.41929000"]},{"commonName":"Carrefour","countryCode":"HT","countryName":"Haiti","stateCode":"OU","coords":["18.54114000","-72.39922000"]},{"commonName":"Cornillon","countryCode":"HT","countryName":"Haiti","stateCode":"OU","coords":["18.67546000","-71.95271000"]},{"commonName":"Croix-des-Bouquets","countryCode":"HT","countryName":"Haiti","stateCode":"OU","coords":["18.57677000","-72.22625000"]},{"commonName":"Delmas 73","countryCode":"HT","countryName":"Haiti","stateCode":"OU","coords":["18.54472000","-72.30278000"]},{"commonName":"Fond Parisien","countryCode":"HT","countryName":"Haiti","stateCode":"OU","coords":["18.50547000","-71.98122000"]},{"commonName":"Fonds Verrettes","countryCode":"HT","countryName":"Haiti","stateCode":"OU","coords":["18.39566000","-71.85634000"]},{"commonName":"Grangwav","countryCode":"HT","countryName":"Haiti","stateCode":"OU","coords":["18.42590000","-72.76995000"]},{"commonName":"Gressier","countryCode":"HT","countryName":"Haiti","stateCode":"OU","coords":["18.54091000","-72.52679000"]},{"commonName":"Kenscoff","countryCode":"HT","countryName":"Haiti","stateCode":"OU","coords":["18.44773000","-72.28398000"]},{"commonName":"Lagonav","countryCode":"HT","countryName":"Haiti","stateCode":"OU","coords":["18.85000000","-73.05000000"]},{"commonName":"Léogâne","countryCode":"HT","countryName":"Haiti","stateCode":"OU","coords":["18.51110000","-72.63343000"]},{"commonName":"Pétionville","countryCode":"HT","countryName":"Haiti","stateCode":"OU","coords":["18.51250000","-72.28528000"]},{"commonName":"Port-au-Prince","countryCode":"HT","countryName":"Haiti","stateCode":"OU","coords":["18.54349000","-72.33881000"]},{"commonName":"Thomazeau","countryCode":"HT","countryName":"Haiti","stateCode":"OU","coords":["18.65297000","-72.09391000"]},{"commonName":"Tigwav","countryCode":"HT","countryName":"Haiti","stateCode":"OU","coords":["18.43117000","-72.86521000"]}]