[{"commonName":"Barma","countryCode":"SL","countryName":"Sierra Leone","stateCode":"E","coords":["8.34959000","-11.33059000"]},{"commonName":"Blama","countryCode":"SL","countryName":"Sierra Leone","stateCode":"E","coords":["7.87481000","-11.34548000"]},{"commonName":"Boajibu","countryCode":"SL","countryName":"Sierra Leone","stateCode":"E","coords":["8.18763000","-11.34026000"]},{"commonName":"Buedu","countryCode":"SL","countryName":"Sierra Leone","stateCode":"E","coords":["8.27960000","-10.37135000"]},{"commonName":"Bunumbu","countryCode":"SL","countryName":"Sierra Leone","stateCode":"E","coords":["8.17421000","-10.86432000"]},{"commonName":"Daru","countryCode":"SL","countryName":"Sierra Leone","stateCode":"E","coords":["7.98976000","-10.84223000"]},{"commonName":"Giehun","countryCode":"SL","countryName":"Sierra Leone","stateCode":"E","coords":["7.88405000","-11.04908000"]},{"commonName":"Gorahun","countryCode":"SL","countryName":"Sierra Leone","stateCode":"E","coords":["7.46439000","-11.23952000"]},{"commonName":"Hangha","countryCode":"SL","countryName":"Sierra Leone","stateCode":"E","coords":["7.93974000","-11.14132000"]},{"commonName":"Jojoima","countryCode":"SL","countryName":"Sierra Leone","stateCode":"E","coords":["7.87815000","-10.78976000"]},{"commonName":"Kailahun","countryCode":"SL","countryName":"Sierra Leone","stateCode":"E","coords":["8.27890000","-10.57300000"]},{"commonName":"Kailahun District","countryCode":"SL","countryName":"Sierra Leone","stateCode":"E","coords":["8.10768000","-10.75146000"]},{"commonName":"Kayima","countryCode":"SL","countryName":"Sierra Leone","stateCode":"E","coords":["8.88790000","-11.15932000"]},{"commonName":"Kenema","countryCode":"SL","countryName":"Sierra Leone","stateCode":"E","coords":["7.87687000","-11.19025000"]},{"commonName":"Kenema District","countryCode":"SL","countryName":"Sierra Leone","stateCode":"E","coords":["7.95171000","-11.19004000"]},{"commonName":"Koidu","countryCode":"SL","countryName":"Sierra Leone","stateCode":"E","coords":["8.64387000","-10.97140000"]},{"commonName":"Kono District","countryCode":"SL","countryName":"Sierra Leone","stateCode":"E","coords":["8.70687000","-10.93368000"]},{"commonName":"Koyima","countryCode":"SL","countryName":"Sierra Leone","stateCode":"E","coords":["8.70552000","-11.02241000"]},{"commonName":"Manowa","countryCode":"SL","countryName":"Sierra Leone","stateCode":"E","coords":["8.17392000","-10.74834000"]},{"commonName":"Mobai","countryCode":"SL","countryName":"Sierra Leone","stateCode":"E","coords":["7.99343000","-10.75355000"]},{"commonName":"Motema","countryCode":"SL","countryName":"Sierra Leone","stateCode":"E","coords":["8.61427000","-11.01252000"]},{"commonName":"Panguma","countryCode":"SL","countryName":"Sierra Leone","stateCode":"E","coords":["8.18507000","-11.13290000"]},{"commonName":"Pendembu","countryCode":"SL","countryName":"Sierra Leone","stateCode":"E","coords":["8.09807000","-10.69429000"]},{"commonName":"Segbwema","countryCode":"SL","countryName":"Sierra Leone","stateCode":"E","coords":["7.99471000","-10.95020000"]},{"commonName":"Simbakoro","countryCode":"SL","countryName":"Sierra Leone","stateCode":"E","coords":["8.61243000","-11.00755000"]},{"commonName":"Tefeya","countryCode":"SL","countryName":"Sierra Leone","stateCode":"E","coords":["8.70395000","-11.21260000"]},{"commonName":"Tombodu","countryCode":"SL","countryName":"Sierra Leone","stateCode":"E","coords":["8.13526000","-10.61960000"]},{"commonName":"Tombu","countryCode":"SL","countryName":"Sierra Leone","stateCode":"E","coords":["8.53991000","-10.73132000"]},{"commonName":"Wima","countryCode":"SL","countryName":"Sierra Leone","stateCode":"E","coords":["8.30052000","-11.20455000"]},{"commonName":"Yengema","countryCode":"SL","countryName":"Sierra Leone","stateCode":"E","coords":["8.71441000","-11.17057000"]}]