[{"commonName":"Ādīs ‘Alem","countryCode":"ET","countryName":"Ethiopia","stateCode":"OR","coords":["9.03333000","38.40000000"]},{"commonName":"Āgaro","countryCode":"ET","countryName":"Ethiopia","stateCode":"OR","coords":["7.85000000","36.65000000"]},{"commonName":"Albany","countryCode":"US","countryName":"United States","stateCode":"OR","coords":["44.63651000","-123.10593000"]},{"commonName":"Allariz","countryCode":"ES","countryName":"Spain","stateCode":"OR","coords":["42.19044000","-7.80175000"]},{"commonName":"Aloha","countryCode":"US","countryName":"United States","stateCode":"OR","coords":["45.49428000","-122.86705000"]},{"commonName":"Altamont","countryCode":"US","countryName":"United States","stateCode":"OR","coords":["42.20681000","-121.73722000"]},{"commonName":"Ambía","countryCode":"ES","countryName":"Spain","stateCode":"OR","coords":["42.20578000","-7.73707000"]},{"commonName":"Amity","countryCode":"US","countryName":"United States","stateCode":"OR","coords":["45.11567000","-123.20733000"]},{"commonName":"Amoeiro","countryCode":"ES","countryName":"Spain","stateCode":"OR","coords":["42.41667000","-7.95000000"]},{"commonName":"Angul","countryCode":"IN","countryName":"India","stateCode":"OR","coords":["20.84089000","85.10192000"]},{"commonName":"Angul District","countryCode":"IN","countryName":"India","stateCode":"OR","coords":["20.84903000","85.06079000"]},{"commonName":"Arnoia A","countryCode":"ES","countryName":"Spain","stateCode":"OR","coords":["42.25666970","-8.14048750"]},{"commonName":"Arsi Zone","countryCode":"ET","countryName":"Ethiopia","stateCode":"OR","coords":["7.50000000","39.50000000"]},{"commonName":"Āsasa","countryCode":"ET","countryName":"Ethiopia","stateCode":"OR","coords":["7.10000000","39.20000000"]},{"commonName":"Āsbe Teferī","countryCode":"ET","countryName":"Ethiopia","stateCode":"OR","coords":["9.08569000","40.86708000"]},{"commonName":"Ashland","countryCode":"US","countryName":"United States","stateCode":"OR","coords":["42.19458000","-122.70948000"]},{"commonName":"Asika","countryCode":"IN","countryName":"India","stateCode":"OR","coords":["19.61114000","84.65998000"]},{"commonName":"Astoria","countryCode":"US","countryName":"United States","stateCode":"OR","coords":["46.18788000","-123.83125000"]},{"commonName":"Athagarh","countryCode":"IN","countryName":"India","stateCode":"OR","coords":["20.51999000","85.62965000"]},{"commonName":"Athena","countryCode":"US","countryName":"United States","stateCode":"OR","coords":["45.81180000","-118.49053000"]},{"commonName":"Aumsville","countryCode":"US","countryName":"United States","stateCode":"OR","coords":["44.84095000","-122.87092000"]},{"commonName":"Avión","countryCode":"ES","countryName":"Spain","stateCode":"OR","coords":["42.38333000","-8.25000000"]},{"commonName":"Bada Barabil","countryCode":"IN","countryName":"India","stateCode":"OR","coords":["22.11186000","85.38684000"]},{"commonName":"Baker City","countryCode":"US","countryName":"United States","stateCode":"OR","coords":["44.77487000","-117.83438000"]},{"commonName":"Baker County","countryCode":"US","countryName":"United States","stateCode":"OR","coords":["44.70923000","-117.67534000"]},{"commonName":"Balangir","countryCode":"IN","countryName":"India","stateCode":"OR","coords":["20.75000000","83.25000000"]},{"commonName":"Balasore","countryCode":"IN","countryName":"India","stateCode":"OR","coords":["21.49266000","86.93348000"]},{"commonName":"Baleshwar","countryCode":"IN","countryName":"India","stateCode":"OR","coords":["21.50000000","86.75000000"]},{"commonName":"Balimila","countryCode":"IN","countryName":"India","stateCode":"OR","coords":["18.25167000","82.10659000"]},{"commonName":"Baltar","countryCode":"ES","countryName":"Spain","stateCode":"OR","coords":["41.95200000","-7.71581000"]},{"commonName":"Balugaon","countryCode":"IN","countryName":"India","stateCode":"OR","coords":["20.17838000","85.11327000"]},{"commonName":"Banapur","countryCode":"IN","countryName":"India","stateCode":"OR","coords":["19.77889000","85.17033000"]},{"commonName":"Bande","countryCode":"ES","countryName":"Spain","stateCode":"OR","coords":["42.03120000","-7.97489000"]},{"commonName":"Bandon","countryCode":"US","countryName":"United States","stateCode":"OR","coords":["43.11900000","-124.40845000"]},{"commonName":"Banki","countryCode":"IN","countryName":"India","stateCode":"OR","coords":["20.37912000","85.52953000"]},{"commonName":"Banks","countryCode":"US","countryName":"United States","stateCode":"OR","coords":["45.61872000","-123.11428000"]},{"commonName":"Baños de Molgas","countryCode":"ES","countryName":"Spain","stateCode":"OR","coords":["42.24148000","-7.67223000"]},{"commonName":"Banposh","countryCode":"IN","countryName":"India","stateCode":"OR","coords":["22.24834000","84.81044000"]},{"commonName":"Baragarh","countryCode":"IN","countryName":"India","stateCode":"OR","coords":["21.33333000","83.61667000"]},{"commonName":"Barbadás","countryCode":"ES","countryName":"Spain","stateCode":"OR","coords":["42.29814510","-7.88712730"]},{"commonName":"Barbil","countryCode":"IN","countryName":"India","stateCode":"OR","coords":["22.10194000","85.37752000"]},{"commonName":"Barco de Valdeorras O","countryCode":"ES","countryName":"Spain","stateCode":"OR","coords":["42.39713180","-6.98534740"]},{"commonName":"Bargarh","countryCode":"IN","countryName":"India","stateCode":"OR","coords":["21.33348000","83.61905000"]},{"commonName":"Barpali","countryCode":"IN","countryName":"India","stateCode":"OR","coords":["21.19005000","83.58721000"]},{"commonName":"Barview","countryCode":"US","countryName":"United States","stateCode":"OR","coords":["43.35428000","-124.31317000"]},{"commonName":"Basudebpur","countryCode":"IN","countryName":"India","stateCode":"OR","coords":["21.11974000","86.72896000"]},{"commonName":"Baud","countryCode":"IN","countryName":"India","stateCode":"OR","coords":["20.83773000","84.32618000"]},{"commonName":"Baudh","countryCode":"IN","countryName":"India","stateCode":"OR","coords":["20.83300000","84.33300000"]},{"commonName":"Bay City","countryCode":"US","countryName":"United States","stateCode":"OR","coords":["45.52260000","-123.88930000"]},{"commonName":"Beade","countryCode":"ES","countryName":"Spain","stateCode":"OR","coords":["42.33074000","-8.12950000"]},{"commonName":"Beariz","countryCode":"ES","countryName":"Spain","stateCode":"OR","coords":["42.46671900","-8.27372960"]},{"commonName":"Beavercreek","countryCode":"US","countryName":"United States","stateCode":"OR","coords":["45.28790000","-122.53564000"]},{"commonName":"Beaverton","countryCode":"US","countryName":"United States","stateCode":"OR","coords":["45.48706000","-122.80371000"]},{"commonName":"Bedelē","countryCode":"ET","countryName":"Ethiopia","stateCode":"OR","coords":["8.45600000","36.35302000"]},{"commonName":"Bedēsa","countryCode":"ET","countryName":"Ethiopia","stateCode":"OR","coords":["8.90000000","40.78333000"]},{"commonName":"Belaguntha","countryCode":"IN","countryName":"India","stateCode":"OR","coords":["19.88249000","84.63801000"]},{"commonName":"Bend","countryCode":"US","countryName":"United States","stateCode":"OR","coords":["44.05817000","-121.31531000"]},{"commonName":"Benton County","countryCode":"US","countryName":"United States","stateCode":"OR","coords":["44.49176000","-123.42931000"]},{"commonName":"Bethany","countryCode":"US","countryName":"United States","stateCode":"OR","coords":["45.55789000","-122.86760000"]},{"commonName":"Bhadrak","countryCode":"IN","countryName":"India","stateCode":"OR","coords":["21.00000000","86.60000000"]},{"commonName":"Bhadrakh","countryCode":"IN","countryName":"India","stateCode":"OR","coords":["21.05447000","86.51560000"]},{"commonName":"Bhanjanagar","countryCode":"IN","countryName":"India","stateCode":"OR","coords":["19.92719000","84.58201000"]},{"commonName":"Bhawanipatna","countryCode":"IN","countryName":"India","stateCode":"OR","coords":["19.90717000","83.16697000"]},{"commonName":"Bhuban","countryCode":"IN","countryName":"India","stateCode":"OR","coords":["20.88197000","85.83334000"]},{"commonName":"Bhubaneswar","countryCode":"IN","countryName":"India","stateCode":"OR","coords":["20.27241000","85.83385000"]},{"commonName":"Binka","countryCode":"IN","countryName":"India","stateCode":"OR","coords":["21.02626000","83.81197000"]},{"commonName":"Birmitrapur","countryCode":"IN","countryName":"India","stateCode":"OR","coords":["22.40000000","84.76667000"]},{"commonName":"Bishoftu","countryCode":"ET","countryName":"Ethiopia","stateCode":"OR","coords":["8.75225000","38.97846000"]},{"commonName":"Blancos Os","countryCode":"ES","countryName":"Spain","stateCode":"OR","coords":["41.99746000","-7.75228560"]},{"commonName":"Boardman","countryCode":"US","countryName":"United States","stateCode":"OR","coords":["45.83986000","-119.70058000"]},{"commonName":"Boborás","countryCode":"ES","countryName":"Spain","stateCode":"OR","coords":["42.43332000","-8.14431000"]},{"commonName":"Bola A","countryCode":"ES","countryName":"Spain","stateCode":"OR","coords":["42.15104360","-7.90482000"]},{"commonName":"Bolanikhodan","countryCode":"IN","countryName":"India","stateCode":"OR","coords":["22.11312000","85.33645000"]},{"commonName":"Bolo O","countryCode":"ES","countryName":"Spain","stateCode":"OR","coords":["42.30168960","-7.10363960"]},{"commonName":"Brahmapur","countryCode":"IN","countryName":"India","stateCode":"OR","coords":["19.31151000","84.79290000"]},{"commonName":"Brajarajnagar","countryCode":"IN","countryName":"India","stateCode":"OR","coords":["21.81667000","83.91667000"]},{"commonName":"Brookings","countryCode":"US","countryName":"United States","stateCode":"OR","coords":["42.05261000","-124.28398000"]},{"commonName":"Brownsville","countryCode":"US","countryName":"United States","stateCode":"OR","coords":["44.39346000","-122.98481000"]},{"commonName":"Buguda","countryCode":"IN","countryName":"India","stateCode":"OR","coords":["19.80806000","84.79084000"]},{"commonName":"Bunker Hill","countryCode":"US","countryName":"United States","stateCode":"OR","coords":["43.35595000","-124.20483000"]},{"commonName":"Burla","countryCode":"IN","countryName":"India","stateCode":"OR","coords":["21.50976000","83.87259000"]},{"commonName":"Burns","countryCode":"US","countryName":"United States","stateCode":"OR","coords":["43.58626000","-119.05410000"]},{"commonName":"Calvos de Randín","countryCode":"ES","countryName":"Spain","stateCode":"OR","coords":["41.90534310","-7.87470560"]},{"commonName":"Canby","countryCode":"US","countryName":"United States","stateCode":"OR","coords":["45.26290000","-122.69259000"]},{"commonName":"Cannon Beach","countryCode":"US","countryName":"United States","stateCode":"OR","coords":["45.89177000","-123.96153000"]},{"commonName":"Canyon City","countryCode":"US","countryName":"United States","stateCode":"OR","coords":["44.38960000","-118.95023000"]},{"commonName":"Canyonville","countryCode":"US","countryName":"United States","stateCode":"OR","coords":["42.92734000","-123.28117000"]},{"commonName":"Carballeda de Avia","countryCode":"ES","countryName":"Spain","stateCode":"OR","coords":["42.32140000","-8.16456000"]},{"commonName":"Carballeda de Valdeorras","countryCode":"ES","countryName":"Spain","stateCode":"OR","coords":["42.32655290","-6.85654270"]},{"commonName":"Carballiño O","countryCode":"ES","countryName":"Spain","stateCode":"OR","coords":["42.43163110","-8.07750760"]},{"commonName":"Carlton","countryCode":"US","countryName":"United States","stateCode":"OR","coords":["45.29428000","-123.17649000"]},{"commonName":"Cartelle","countryCode":"ES","countryName":"Spain","stateCode":"OR","coords":["42.25109000","-8.07062000"]},{"commonName":"Cascade Locks","countryCode":"US","countryName":"United States","stateCode":"OR","coords":["45.66984000","-121.89064000"]},{"commonName":"Castrelo de Miño","countryCode":"ES","countryName":"Spain","stateCode":"OR","coords":["42.29798000","-8.06697000"]},{"commonName":"Castrelo do Val","countryCode":"ES","countryName":"Spain","stateCode":"OR","coords":["41.98961620","-7.42258810"]},{"commonName":"Castro Caldelas","countryCode":"ES","countryName":"Spain","stateCode":"OR","coords":["42.37366000","-7.42578000"]},{"commonName":"Cave Junction","countryCode":"US","countryName":"United States","stateCode":"OR","coords":["42.16289000","-123.64812000"]},{"commonName":"Cedar Hills","countryCode":"US","countryName":"United States","stateCode":"OR","coords":["45.50484000","-122.79843000"]},{"commonName":"Cedar Mill","countryCode":"US","countryName":"United States","stateCode":"OR","coords":["45.52484000","-122.81093000"]},{"commonName":"Celanova","countryCode":"ES","countryName":"Spain","stateCode":"OR","coords":["42.15303000","-7.95513000"]},{"commonName":"Cenlle","countryCode":"ES","countryName":"Spain","stateCode":"OR","coords":["42.34183000","-8.08982000"]},{"commonName":"Central Point","countryCode":"US","countryName":"United States","stateCode":"OR","coords":["42.37596000","-122.91643000"]},{"commonName":"Champua","countryCode":"IN","countryName":"India","stateCode":"OR","coords":["22.06734000","85.66463000"]},{"commonName":"Chandbali","countryCode":"IN","countryName":"India","stateCode":"OR","coords":["20.77519000","86.74139000"]},{"commonName":"Chandrexa de Queixa","countryCode":"ES","countryName":"Spain","stateCode":"OR","coords":["42.25477690","-7.38145520"]},{"commonName":"Chatrapur","countryCode":"IN","countryName":"India","stateCode":"OR","coords":["19.35574000","84.98359000"]},{"commonName":"Chenoweth","countryCode":"US","countryName":"United States","stateCode":"OR","coords":["45.62762000","-121.24341000"]},{"commonName":"Chikitigarh","countryCode":"IN","countryName":"India","stateCode":"OR","coords":["19.20233000","84.61450000"]},{"commonName":"Chittarkonda","countryCode":"IN","countryName":"India","stateCode":"OR","coords":["18.12533000","82.10890000"]},{"commonName":"Clackamas","countryCode":"US","countryName":"United States","stateCode":"OR","coords":["45.40762000","-122.57037000"]},{"commonName":"Clackamas County","countryCode":"US","countryName":"United States","stateCode":"OR","coords":["45.18816000","-122.22094000"]},{"commonName":"Clatskanie","countryCode":"US","countryName":"United States","stateCode":"OR","coords":["46.10122000","-123.20679000"]},{"commonName":"Clatsop County","countryCode":"US","countryName":"United States","stateCode":"OR","coords":["46.01747000","-123.71677000"]},{"commonName":"Coburg","countryCode":"US","countryName":"United States","stateCode":"OR","coords":["44.13707000","-123.06648000"]},{"commonName":"Coles","countryCode":"ES","countryName":"Spain","stateCode":"OR","coords":["42.40000000","-7.83333000"]},{"commonName":"Columbia City","countryCode":"US","countryName":"United States","stateCode":"OR","coords":["45.89011000","-122.80705000"]},{"commonName":"Columbia County","countryCode":"US","countryName":"United States","stateCode":"OR","coords":["45.94377000","-123.08805000"]},{"commonName":"Condon","countryCode":"US","countryName":"United States","stateCode":"OR","coords":["45.23430000","-120.18503000"]},{"commonName":"Coos Bay","countryCode":"US","countryName":"United States","stateCode":"OR","coords":["43.36650000","-124.21789000"]},{"commonName":"Coos County","countryCode":"US","countryName":"United States","stateCode":"OR","coords":["43.18501000","-124.09333000"]},{"commonName":"Coquille","countryCode":"US","countryName":"United States","stateCode":"OR","coords":["43.17705000","-124.18761000"]},{"commonName":"Cornelius","countryCode":"US","countryName":"United States","stateCode":"OR","coords":["45.51984000","-123.05983000"]},{"commonName":"Cortegada","countryCode":"ES","countryName":"Spain","stateCode":"OR","coords":["42.20732230","-8.17012000"]},{"commonName":"Corvallis","countryCode":"US","countryName":"United States","stateCode":"OR","coords":["44.56457000","-123.26204000"]},{"commonName":"Cottage Grove","countryCode":"US","countryName":"United States","stateCode":"OR","coords":["43.79762000","-123.05952000"]},{"commonName":"Creswell","countryCode":"US","countryName":"United States","stateCode":"OR","coords":["43.91790000","-123.02453000"]},{"commonName":"Crook County","countryCode":"US","countryName":"United States","stateCode":"OR","coords":["44.14219000","-120.35658000"]},{"commonName":"Cualedro","countryCode":"ES","countryName":"Spain","stateCode":"OR","coords":["41.98897000","-7.59464000"]},{"commonName":"Culp Creek","countryCode":"US","countryName":"United States","stateCode":"OR","coords":["43.70346000","-122.84757000"]},{"commonName":"Culver","countryCode":"US","countryName":"United States","stateCode":"OR","coords":["44.52568000","-121.21310000"]},{"commonName":"Curry County","countryCode":"US","countryName":"United States","stateCode":"OR","coords":["42.46661000","-124.21534000"]},{"commonName":"Cuttack","countryCode":"IN","countryName":"India","stateCode":"OR","coords":["20.50000000","86.25000000"]},{"commonName":"Daitari","countryCode":"IN","countryName":"India","stateCode":"OR","coords":["21.10000000","85.75000000"]},{"commonName":"Dallas","countryCode":"US","countryName":"United States","stateCode":"OR","coords":["44.91928000","-123.31705000"]},{"commonName":"Damascus","countryCode":"US","countryName":"United States","stateCode":"OR","coords":["45.41762000","-122.45898000"]},{"commonName":"Dayton","countryCode":"US","countryName":"United States","stateCode":"OR","coords":["45.22067000","-123.07621000"]},{"commonName":"Deder","countryCode":"ET","countryName":"Ethiopia","stateCode":"OR","coords":["9.31168000","41.44301000"]},{"commonName":"Dembī Dolo","countryCode":"ET","countryName":"Ethiopia","stateCode":"OR","coords":["8.53333000","34.80000000"]},{"commonName":"Deogarh","countryCode":"IN","countryName":"India","stateCode":"OR","coords":["21.53827000","84.73337000"]},{"commonName":"Depoe Bay","countryCode":"US","countryName":"United States","stateCode":"OR","coords":["44.80845000","-124.06317000"]},{"commonName":"Deschutes County","countryCode":"US","countryName":"United States","stateCode":"OR","coords":["43.91488000","-121.22789000"]},{"commonName":"Deschutes River Woods","countryCode":"US","countryName":"United States","stateCode":"OR","coords":["43.99151000","-121.35836000"]},{"commonName":"Dhenkanal","countryCode":"IN","countryName":"India","stateCode":"OR","coords":["20.75000000","85.50000000"]},{"commonName":"Digapahandi","countryCode":"IN","countryName":"India","stateCode":"OR","coords":["19.37275000","84.57184000"]},{"commonName":"Dodola","countryCode":"ET","countryName":"Ethiopia","stateCode":"OR","coords":["6.98333000","39.18333000"]},{"commonName":"Donald","countryCode":"US","countryName":"United States","stateCode":"OR","coords":["45.22234000","-122.83926000"]},{"commonName":"Douglas County","countryCode":"US","countryName":"United States","stateCode":"OR","coords":["43.28536000","-123.17942000"]},{"commonName":"Drain","countryCode":"US","countryName":"United States","stateCode":"OR","coords":["43.65873000","-123.31870000"]},{"commonName":"Dundee","countryCode":"US","countryName":"United States","stateCode":"OR","coords":["45.27817000","-123.01094000"]},{"commonName":"Dunes City","countryCode":"US","countryName":"United States","stateCode":"OR","coords":["43.88318000","-124.11512000"]},{"commonName":"Durham","countryCode":"US","countryName":"United States","stateCode":"OR","coords":["45.40206000","-122.75287000"]},{"commonName":"Eagle Point","countryCode":"US","countryName":"United States","stateCode":"OR","coords":["42.47263000","-122.80282000"]},{"commonName":"East Harerghe Zone","countryCode":"ET","countryName":"Ethiopia","stateCode":"OR","coords":["8.70114000","42.00241000"]},{"commonName":"East Shewa Zone","countryCode":"ET","countryName":"Ethiopia","stateCode":"OR","coords":["8.21353000","38.84809000"]},{"commonName":"East Wellega Zone","countryCode":"ET","countryName":"Ethiopia","stateCode":"OR","coords":["9.51928000","36.75762000"]},{"commonName":"Elgin","countryCode":"US","countryName":"United States","stateCode":"OR","coords":["45.56486000","-117.91743000"]},{"commonName":"Enterprise","countryCode":"US","countryName":"United States","stateCode":"OR","coords":["45.42626000","-117.27878000"]},{"commonName":"Entrimo","countryCode":"ES","countryName":"Spain","stateCode":"OR","coords":["41.93297000","-8.11725000"]},{"commonName":"Esgos","countryCode":"ES","countryName":"Spain","stateCode":"OR","coords":["42.32549000","-7.69691000"]},{"commonName":"Estacada","countryCode":"US","countryName":"United States","stateCode":"OR","coords":["45.28957000","-122.33370000"]},{"commonName":"Eugene","countryCode":"US","countryName":"United States","stateCode":"OR","coords":["44.05207000","-123.08675000"]},{"commonName":"Fairview","countryCode":"US","countryName":"United States","stateCode":"OR","coords":["45.53845000","-122.43398000"]},{"commonName":"Fichē","countryCode":"ET","countryName":"Ethiopia","stateCode":"OR","coords":["9.80000000","38.73333000"]},{"commonName":"Florence","countryCode":"US","countryName":"United States","stateCode":"OR","coords":["43.98262000","-124.09984000"]},{"commonName":"Forest Grove","countryCode":"US","countryName":"United States","stateCode":"OR","coords":["45.51984000","-123.11066000"]},{"commonName":"Fossil","countryCode":"US","countryName":"United States","stateCode":"OR","coords":["44.99819000","-120.21614000"]},{"commonName":"Four Corners","countryCode":"US","countryName":"United States","stateCode":"OR","coords":["44.92790000","-122.98371000"]},{"commonName":"Fruitdale","countryCode":"US","countryName":"United States","stateCode":"OR","coords":["42.42206000","-123.30811000"]},{"commonName":"Gajapati","countryCode":"IN","countryName":"India","stateCode":"OR","coords":["18.91000000","84.20000000"]},{"commonName":"Ganjam","countryCode":"IN","countryName":"India","stateCode":"OR","coords":["19.38705000","85.05079000"]},{"commonName":"Garden Home-Whitford","countryCode":"US","countryName":"United States","stateCode":"OR","coords":["45.46400000","-122.75891000"]},{"commonName":"Gearhart","countryCode":"US","countryName":"United States","stateCode":"OR","coords":["46.02427000","-123.91125000"]},{"commonName":"Gebre Guracha","countryCode":"ET","countryName":"Ethiopia","stateCode":"OR","coords":["9.80000000","38.40000000"]},{"commonName":"Gēdo","countryCode":"ET","countryName":"Ethiopia","stateCode":"OR","coords":["9.01667000","37.45000000"]},{"commonName":"Gelemso","countryCode":"ET","countryName":"Ethiopia","stateCode":"OR","coords":["8.81667000","40.51667000"]},{"commonName":"Genet","countryCode":"ET","countryName":"Ethiopia","stateCode":"OR","coords":["9.06667000","38.50000000"]},{"commonName":"Gervais","countryCode":"US","countryName":"United States","stateCode":"OR","coords":["45.10818000","-122.89760000"]},{"commonName":"Gilliam County","countryCode":"US","countryName":"United States","stateCode":"OR","coords":["45.37806000","-120.21087000"]},{"commonName":"Gimbi","countryCode":"ET","countryName":"Ethiopia","stateCode":"OR","coords":["9.17031000","35.83491000"]},{"commonName":"Ginir","countryCode":"ET","countryName":"Ethiopia","stateCode":"OR","coords":["7.13952000","40.71083000"]},{"commonName":"Gladstone","countryCode":"US","countryName":"United States","stateCode":"OR","coords":["45.38068000","-122.59481000"]},{"commonName":"Glide","countryCode":"US","countryName":"United States","stateCode":"OR","coords":["43.30151000","-123.10118000"]},{"commonName":"Goba","countryCode":"ET","countryName":"Ethiopia","stateCode":"OR","coords":["7.01667000","39.98333000"]},{"commonName":"Gold Beach","countryCode":"US","countryName":"United States","stateCode":"OR","coords":["42.40733000","-124.42177000"]},{"commonName":"Gold Hill","countryCode":"US","countryName":"United States","stateCode":"OR","coords":["42.43179000","-123.05060000"]},{"commonName":"Gomesende","countryCode":"ES","countryName":"Spain","stateCode":"OR","coords":["42.16322380","-8.10348050"]},{"commonName":"Gopalpur","countryCode":"IN","countryName":"India","stateCode":"OR","coords":["19.25861000","84.90517000"]},{"commonName":"Gorē","countryCode":"ET","countryName":"Ethiopia","stateCode":"OR","coords":["8.15000000","35.53333000"]},{"commonName":"Grand Ronde","countryCode":"US","countryName":"United States","stateCode":"OR","coords":["45.06011000","-123.60928000"]},{"commonName":"Grant County","countryCode":"US","countryName":"United States","stateCode":"OR","coords":["44.49125000","-119.00738000"]},{"commonName":"Grants Pass","countryCode":"US","countryName":"United States","stateCode":"OR","coords":["42.43933000","-123.33067000"]},{"commonName":"Green","countryCode":"US","countryName":"United States","stateCode":"OR","coords":["43.16039000","-123.36785000"]},{"commonName":"Gresham","countryCode":"US","countryName":"United States","stateCode":"OR","coords":["45.49818000","-122.43148000"]},{"commonName":"Gudari","countryCode":"IN","countryName":"India","stateCode":"OR","coords":["19.34762000","83.78128000"]},{"commonName":"Gudiña A","countryCode":"ES","countryName":"Spain","stateCode":"OR","coords":["42.06057390","-7.13930290"]},{"commonName":"Guji Zone","countryCode":"ET","countryName":"Ethiopia","stateCode":"OR","coords":["5.58800000","39.06700000"]},{"commonName":"Gunupur","countryCode":"IN","countryName":"India","stateCode":"OR","coords":["19.08040000","83.80879000"]},{"commonName":"Hāgere Hiywet","countryCode":"ET","countryName":"Ethiopia","stateCode":"OR","coords":["8.98333000","37.85000000"]},{"commonName":"Hagere Maryam","countryCode":"ET","countryName":"Ethiopia","stateCode":"OR","coords":["5.63418000","38.23603000"]},{"commonName":"Happy Valley","countryCode":"US","countryName":"United States","stateCode":"OR","coords":["45.44679000","-122.53037000"]},{"commonName":"Harbor","countryCode":"US","countryName":"United States","stateCode":"OR","coords":["42.05317000","-124.26759000"]},{"commonName":"Harney County","countryCode":"US","countryName":"United States","stateCode":"OR","coords":["43.06402000","-118.96787000"]},{"commonName":"Harrisburg","countryCode":"US","countryName":"United States","stateCode":"OR","coords":["44.27401000","-123.17065000"]},{"commonName":"Hayesville","countryCode":"US","countryName":"United States","stateCode":"OR","coords":["44.98595000","-122.98287000"]},{"commonName":"Heppner","countryCode":"US","countryName":"United States","stateCode":"OR","coords":["45.35318000","-119.55780000"]},{"commonName":"Hermiston","countryCode":"US","countryName":"United States","stateCode":"OR","coords":["45.84041000","-119.28946000"]},{"commonName":"Hillsboro","countryCode":"US","countryName":"United States","stateCode":"OR","coords":["45.52289000","-122.98983000"]},{"commonName":"Hines","countryCode":"US","countryName":"United States","stateCode":"OR","coords":["43.56404000","-119.08105000"]},{"commonName":"Hinjilikatu","countryCode":"IN","countryName":"India","stateCode":"OR","coords":["19.48166000","84.74489000"]},{"commonName":"Hirakud","countryCode":"IN","countryName":"India","stateCode":"OR","coords":["21.52502000","83.87275000"]},{"commonName":"Hīrna","countryCode":"ET","countryName":"Ethiopia","stateCode":"OR","coords":["9.21667000","41.10000000"]},{"commonName":"Hood River","countryCode":"US","countryName":"United States","stateCode":"OR","coords":["45.70540000","-121.52146000"]},{"commonName":"Hood River County","countryCode":"US","countryName":"United States","stateCode":"OR","coords":["45.51911000","-121.65111000"]},{"commonName":"Hubbard","countryCode":"US","countryName":"United States","stateCode":"OR","coords":["45.18234000","-122.80787000"]},{"commonName":"Huruta","countryCode":"ET","countryName":"Ethiopia","stateCode":"OR","coords":["8.15000000","39.35000000"]},{"commonName":"Illubabor Zone","countryCode":"ET","countryName":"Ethiopia","stateCode":"OR","coords":["8.27526000","35.75596000"]},{"commonName":"Independence","countryCode":"US","countryName":"United States","stateCode":"OR","coords":["44.85123000","-123.18677000"]},{"commonName":"Irixo O","countryCode":"ES","countryName":"Spain","stateCode":"OR","coords":["42.33578930","-7.86388100"]},{"commonName":"Irrigon","countryCode":"US","countryName":"United States","stateCode":"OR","coords":["45.89569000","-119.49141000"]},{"commonName":"Island City","countryCode":"US","countryName":"United States","stateCode":"OR","coords":["45.34097000","-118.04466000"]},{"commonName":"Jackson County","countryCode":"US","countryName":"United States","stateCode":"OR","coords":["42.43215000","-122.72843000"]},{"commonName":"Jacksonville","countryCode":"US","countryName":"United States","stateCode":"OR","coords":["42.31346000","-122.96699000"]},{"commonName":"Jagatsinghpur","countryCode":"IN","countryName":"India","stateCode":"OR","coords":["20.20000000","86.30000000"]},{"commonName":"Jajpur","countryCode":"IN","countryName":"India","stateCode":"OR","coords":["20.84149000","86.31237000"]},{"commonName":"Jaleshwar","countryCode":"IN","countryName":"India","stateCode":"OR","coords":["21.80176000","87.22250000"]},{"commonName":"Jatani","countryCode":"IN","countryName":"India","stateCode":"OR","coords":["20.15975000","85.70742000"]},{"commonName":"Jefferson","countryCode":"US","countryName":"United States","stateCode":"OR","coords":["44.71957000","-123.01037000"]},{"commonName":"Jefferson County","countryCode":"US","countryName":"United States","stateCode":"OR","coords":["44.62941000","-121.17541000"]},{"commonName":"Jennings Lodge","countryCode":"US","countryName":"United States","stateCode":"OR","coords":["45.39123000","-122.61259000"]},{"commonName":"Jeypore","countryCode":"IN","countryName":"India","stateCode":"OR","coords":["18.85630000","82.57160000"]},{"commonName":"Jharsuguda","countryCode":"IN","countryName":"India","stateCode":"OR","coords":["21.85531000","84.00698000"]},{"commonName":"Jharsuguda District","countryCode":"IN","countryName":"India","stateCode":"OR","coords":["21.85000000","84.00000000"]},{"commonName":"Jimma","countryCode":"ET","countryName":"Ethiopia","stateCode":"OR","coords":["7.67344000","36.83441000"]},{"commonName":"Jimma Zone","countryCode":"ET","countryName":"Ethiopia","stateCode":"OR","coords":["7.66667000","37.00000000"]},{"commonName":"John Day","countryCode":"US","countryName":"United States","stateCode":"OR","coords":["44.41599000","-118.95301000"]},{"commonName":"Joseph","countryCode":"US","countryName":"United States","stateCode":"OR","coords":["45.35432000","-117.22961000"]},{"commonName":"Josephine County","countryCode":"US","countryName":"United States","stateCode":"OR","coords":["42.36546000","-123.55558000"]},{"commonName":"Junction City","countryCode":"US","countryName":"United States","stateCode":"OR","coords":["44.21929000","-123.20565000"]},{"commonName":"Kaintragarh","countryCode":"IN","countryName":"India","stateCode":"OR","coords":["20.72115000","84.53514000"]},{"commonName":"Kalahandi","countryCode":"IN","countryName":"India","stateCode":"OR","coords":["19.75000000","83.00000000"]},{"commonName":"Kamakhyanagar","countryCode":"IN","countryName":"India","stateCode":"OR","coords":["20.93385000","85.54489000"]},{"commonName":"Kandhamal","countryCode":"IN","countryName":"India","stateCode":"OR","coords":["20.30000000","84.00000000"]},{"commonName":"Kantabanji","countryCode":"IN","countryName":"India","stateCode":"OR","coords":["20.46709000","82.92042000"]},{"commonName":"Kantilo","countryCode":"IN","countryName":"India","stateCode":"OR","coords":["20.36152000","85.19212000"]},{"commonName":"Keizer","countryCode":"US","countryName":"United States","stateCode":"OR","coords":["44.99012000","-123.02621000"]},{"commonName":"Kendrapara","countryCode":"IN","countryName":"India","stateCode":"OR","coords":["20.50000000","86.50000000"]},{"commonName":"Kendujhar","countryCode":"IN","countryName":"India","stateCode":"OR","coords":["21.50000000","85.50000000"]},{"commonName":"Kenton","countryCode":"US","countryName":"United States","stateCode":"OR","coords":["45.58178000","-122.68149000"]},{"commonName":"Kesinga","countryCode":"IN","countryName":"India","stateCode":"OR","coords":["20.18778000","83.21949000"]},{"commonName":"Khallikot","countryCode":"IN","countryName":"India","stateCode":"OR","coords":["19.60908000","85.08609000"]},{"commonName":"Kharhial","countryCode":"IN","countryName":"India","stateCode":"OR","coords":["20.28845000","82.76060000"]},{"commonName":"Khordha","countryCode":"IN","countryName":"India","stateCode":"OR","coords":["20.20000000","85.60000000"]},{"commonName":"Khurda","countryCode":"IN","countryName":"India","stateCode":"OR","coords":["20.18268000","85.61629000"]},{"commonName":"Kibre Mengist","countryCode":"ET","countryName":"Ethiopia","stateCode":"OR","coords":["5.88333000","38.98333000"]},{"commonName":"King City","countryCode":"US","countryName":"United States","stateCode":"OR","coords":["45.40262000","-122.80399000"]},{"commonName":"Kiri Buru","countryCode":"IN","countryName":"India","stateCode":"OR","coords":["22.08333000","85.35000000"]},{"commonName":"Klamath County","countryCode":"US","countryName":"United States","stateCode":"OR","coords":["42.68634000","-121.65013000"]},{"commonName":"Klamath Falls","countryCode":"US","countryName":"United States","stateCode":"OR","coords":["42.22487000","-121.78167000"]},{"commonName":"Kodala","countryCode":"IN","countryName":"India","stateCode":"OR","coords":["19.62425000","84.94075000"]},{"commonName":"Kofelē","countryCode":"ET","countryName":"Ethiopia","stateCode":"OR","coords":["7.06667000","38.78333000"]},{"commonName":"Konarka","countryCode":"IN","countryName":"India","stateCode":"OR","coords":["19.89758000","86.11413000"]},{"commonName":"Koraput","countryCode":"IN","countryName":"India","stateCode":"OR","coords":["19.00000000","83.00000000"]},{"commonName":"Kuchaiburi","countryCode":"IN","countryName":"India","stateCode":"OR","coords":["22.26675000","86.17385000"]},{"commonName":"Kuchinda","countryCode":"IN","countryName":"India","stateCode":"OR","coords":["21.74356000","84.34848000"]},{"commonName":"La Grande","countryCode":"US","countryName":"United States","stateCode":"OR","coords":["45.32458000","-118.08772000"]},{"commonName":"La Pine","countryCode":"US","countryName":"United States","stateCode":"OR","coords":["43.67040000","-121.50364000"]},{"commonName":"Lafayette","countryCode":"US","countryName":"United States","stateCode":"OR","coords":["45.24428000","-123.11483000"]},{"commonName":"Lake County","countryCode":"US","countryName":"United States","stateCode":"OR","coords":["42.79339000","-120.38747000"]},{"commonName":"Lake Oswego","countryCode":"US","countryName":"United States","stateCode":"OR","coords":["45.42067000","-122.67065000"]},{"commonName":"Lakeside","countryCode":"US","countryName":"United States","stateCode":"OR","coords":["43.57567000","-124.17511000"]},{"commonName":"Lakeview","countryCode":"US","countryName":"United States","stateCode":"OR","coords":["42.18877000","-120.34579000"]},{"commonName":"Lane County","countryCode":"US","countryName":"United States","stateCode":"OR","coords":["43.94155000","-122.87655000"]},{"commonName":"Larouco","countryCode":"ES","countryName":"Spain","stateCode":"OR","coords":["42.34651170","-7.16084480"]},{"commonName":"Laza","countryCode":"ES","countryName":"Spain","stateCode":"OR","coords":["42.06136000","-7.46200000"]},{"commonName":"Lebanon","countryCode":"US","countryName":"United States","stateCode":"OR","coords":["44.53651000","-122.90703000"]},{"commonName":"Leiro","countryCode":"ES","countryName":"Spain","stateCode":"OR","coords":["42.36937040","-8.14478040"]},{"commonName":"Lents","countryCode":"US","countryName":"United States","stateCode":"OR","coords":["45.47984000","-122.56731000"]},{"commonName":"Lincoln Beach","countryCode":"US","countryName":"United States","stateCode":"OR","coords":["44.85039000","-124.04678000"]},{"commonName":"Lincoln City","countryCode":"US","countryName":"United States","stateCode":"OR","coords":["44.95816000","-124.01789000"]},{"commonName":"Lincoln County","countryCode":"US","countryName":"United States","stateCode":"OR","coords":["44.64568000","-123.90770000"]},{"commonName":"Linn County","countryCode":"US","countryName":"United States","stateCode":"OR","coords":["44.48857000","-122.53419000"]},{"commonName":"Lobeira","countryCode":"ES","countryName":"Spain","stateCode":"OR","coords":["41.98645690","-8.03958980"]},{"commonName":"Lobios","countryCode":"ES","countryName":"Spain","stateCode":"OR","coords":["42.40746000","-7.53164000"]},{"commonName":"Lowell","countryCode":"US","countryName":"United States","stateCode":"OR","coords":["43.91846000","-122.78368000"]},{"commonName":"Luintra","countryCode":"ES","countryName":"Spain","stateCode":"OR","coords":["42.40964000","-7.72682000"]},{"commonName":"Lyons","countryCode":"US","countryName":"United States","stateCode":"OR","coords":["44.77457000","-122.61509000"]},{"commonName":"Maceda","countryCode":"ES","countryName":"Spain","stateCode":"OR","coords":["42.26972000","-7.65052000"]},{"commonName":"Madras","countryCode":"US","countryName":"United States","stateCode":"OR","coords":["44.63345000","-121.12949000"]},{"commonName":"Malheur County","countryCode":"US","countryName":"United States","stateCode":"OR","coords":["43.19341000","-117.62307000"]},{"commonName":"Malkangiri","countryCode":"IN","countryName":"India","stateCode":"OR","coords":["18.25000000","81.95000000"]},{"commonName":"Manzaneda","countryCode":"ES","countryName":"Spain","stateCode":"OR","coords":["42.30962000","-7.23209000"]},{"commonName":"Marion County","countryCode":"US","countryName":"United States","stateCode":"OR","coords":["44.90319000","-122.58473000"]},{"commonName":"Maside","countryCode":"ES","countryName":"Spain","stateCode":"OR","coords":["42.41031000","-8.02582000"]},{"commonName":"Mayurbhanj","countryCode":"IN","countryName":"India","stateCode":"OR","coords":["21.75000000","86.50000000"]},{"commonName":"McMinnville","countryCode":"US","countryName":"United States","stateCode":"OR","coords":["45.21012000","-123.19872000"]},{"commonName":"Medford","countryCode":"US","countryName":"United States","stateCode":"OR","coords":["42.32652000","-122.87559000"]},{"commonName":"Mēga","countryCode":"ET","countryName":"Ethiopia","stateCode":"OR","coords":["4.05000000","38.30000000"]},{"commonName":"Melón","countryCode":"ES","countryName":"Spain","stateCode":"OR","coords":["42.26016000","-8.21400000"]},{"commonName":"Mendī","countryCode":"ET","countryName":"Ethiopia","stateCode":"OR","coords":["9.80000000","35.10000000"]},{"commonName":"Merca A","countryCode":"ES","countryName":"Spain","stateCode":"OR","coords":["42.22228080","-7.90548160"]},{"commonName":"Merlin","countryCode":"US","countryName":"United States","stateCode":"OR","coords":["42.51734000","-123.41979000"]},{"commonName":"Metahāra","countryCode":"ET","countryName":"Ethiopia","stateCode":"OR","coords":["8.90000000","39.91667000"]},{"commonName":"Metu","countryCode":"ET","countryName":"Ethiopia","stateCode":"OR","coords":["8.30000000","35.58333000"]},{"commonName":"Metzger","countryCode":"US","countryName":"United States","stateCode":"OR","coords":["45.44651000","-122.75899000"]},{"commonName":"Mezquita A","countryCode":"ES","countryName":"Spain","stateCode":"OR","coords":["42.34697080","-7.85456320"]},{"commonName":"Mill City","countryCode":"US","countryName":"United States","stateCode":"OR","coords":["44.75401000","-122.47814000"]},{"commonName":"Millersburg","countryCode":"US","countryName":"United States","stateCode":"OR","coords":["44.68095000","-123.06148000"]},{"commonName":"Milton-Freewater","countryCode":"US","countryName":"United States","stateCode":"OR","coords":["45.93263000","-118.38774000"]},{"commonName":"Milwaukie","countryCode":"US","countryName":"United States","stateCode":"OR","coords":["45.44623000","-122.63926000"]},{"commonName":"Mission","countryCode":"US","countryName":"United States","stateCode":"OR","coords":["45.67041000","-118.68359000"]},{"commonName":"Mojo","countryCode":"ET","countryName":"Ethiopia","stateCode":"OR","coords":["8.58679000","39.12111000"]},{"commonName":"Molalla","countryCode":"US","countryName":"United States","stateCode":"OR","coords":["45.14734000","-122.57703000"]},{"commonName":"Monmouth","countryCode":"US","countryName":"United States","stateCode":"OR","coords":["44.84845000","-123.23399000"]},{"commonName":"Montederramo","countryCode":"ES","countryName":"Spain","stateCode":"OR","coords":["42.27554000","-7.50138000"]},{"commonName":"Monterrei","countryCode":"ES","countryName":"Spain","stateCode":"OR","coords":["41.94701790","-7.44923960"]},{"commonName":"Moro","countryCode":"US","countryName":"United States","stateCode":"OR","coords":["45.48401000","-120.73117000"]},{"commonName":"Morrow County","countryCode":"US","countryName":"United States","stateCode":"OR","coords":["45.41883000","-119.58430000"]},{"commonName":"Mount Angel","countryCode":"US","countryName":"United States","stateCode":"OR","coords":["45.06790000","-122.80009000"]},{"commonName":"Mount Hood Village","countryCode":"US","countryName":"United States","stateCode":"OR","coords":["45.35540000","-121.98064000"]},{"commonName":"Muiños","countryCode":"ES","countryName":"Spain","stateCode":"OR","coords":["41.95609000","-7.97396000"]},{"commonName":"Mulino","countryCode":"US","countryName":"United States","stateCode":"OR","coords":["45.22151000","-122.58203000"]},{"commonName":"Multnomah County","countryCode":"US","countryName":"United States","stateCode":"OR","coords":["45.54687000","-122.41534000"]},{"commonName":"Myrtle Creek","countryCode":"US","countryName":"United States","stateCode":"OR","coords":["43.02012000","-123.29312000"]},{"commonName":"Myrtle Point","countryCode":"US","countryName":"United States","stateCode":"OR","coords":["43.06483000","-124.13899000"]},{"commonName":"Nabarangpur","countryCode":"IN","countryName":"India","stateCode":"OR","coords":["19.23330000","82.55000000"]},{"commonName":"Nayagarh","countryCode":"IN","countryName":"India","stateCode":"OR","coords":["20.12882000","85.09626000"]},{"commonName":"Nayagarh District","countryCode":"IN","countryName":"India","stateCode":"OR","coords":["20.13000000","85.10000000"]},{"commonName":"Nazrēt","countryCode":"ET","countryName":"Ethiopia","stateCode":"OR","coords":["8.55000000","39.26667000"]},{"commonName":"Nejo","countryCode":"ET","countryName":"Ethiopia","stateCode":"OR","coords":["9.50000000","35.50000000"]},{"commonName":"New Hope","countryCode":"US","countryName":"United States","stateCode":"OR","coords":["42.36234000","-123.36784000"]},{"commonName":"Newberg","countryCode":"US","countryName":"United States","stateCode":"OR","coords":["45.30012000","-122.97316000"]},{"commonName":"Newport","countryCode":"US","countryName":"United States","stateCode":"OR","coords":["44.63678000","-124.05345000"]},{"commonName":"Nilgiri","countryCode":"IN","countryName":"India","stateCode":"OR","coords":["21.46235000","86.76794000"]},{"commonName":"Nimaparha","countryCode":"IN","countryName":"India","stateCode":"OR","coords":["20.05756000","86.00436000"]},{"commonName":"Nogueira de Ramuín","countryCode":"ES","countryName":"Spain","stateCode":"OR","coords":["42.41712000","-7.74982000"]},{"commonName":"North Bend","countryCode":"US","countryName":"United States","stateCode":"OR","coords":["43.40650000","-124.22428000"]},{"commonName":"North Plains","countryCode":"US","countryName":"United States","stateCode":"OR","coords":["45.59706000","-122.99344000"]},{"commonName":"North Portland","countryCode":"US","countryName":"United States","stateCode":"OR","coords":["45.61039000","-122.70343000"]},{"commonName":"North Shewa Zone","countryCode":"ET","countryName":"Ethiopia","stateCode":"OR","coords":["9.66915000","38.81240000"]},{"commonName":"Nowrangapur","countryCode":"IN","countryName":"India","stateCode":"OR","coords":["19.23114000","82.54826000"]},{"commonName":"Nuapada","countryCode":"IN","countryName":"India","stateCode":"OR","coords":["20.60000000","82.50000000"]},{"commonName":"Nyssa","countryCode":"US","countryName":"United States","stateCode":"OR","coords":["43.87683000","-116.99488000"]},{"commonName":"O Barco de Valdeorras","countryCode":"ES","countryName":"Spain","stateCode":"OR","coords":["42.41642000","-6.99005000"]},{"commonName":"O Carballiño","countryCode":"ES","countryName":"Spain","stateCode":"OR","coords":["42.43163000","-8.07899000"]},{"commonName":"Oak Grove","countryCode":"US","countryName":"United States","stateCode":"OR","coords":["45.41679000","-122.64009000"]},{"commonName":"Oak Hills","countryCode":"US","countryName":"United States","stateCode":"OR","coords":["45.54123000","-122.84121000"]},{"commonName":"Oakridge","countryCode":"US","countryName":"United States","stateCode":"OR","coords":["43.74651000","-122.46172000"]},{"commonName":"Oatfield","countryCode":"US","countryName":"United States","stateCode":"OR","coords":["45.41418000","-122.60007000"]},{"commonName":"Odell","countryCode":"US","countryName":"United States","stateCode":"OR","coords":["45.62706000","-121.54313000"]},{"commonName":"Oimbra","countryCode":"ES","countryName":"Spain","stateCode":"OR","coords":["41.88554000","-7.47216000"]},{"commonName":"Ontario","countryCode":"US","countryName":"United States","stateCode":"OR","coords":["44.02655000","-116.96294000"]},{"commonName":"Oregon City","countryCode":"US","countryName":"United States","stateCode":"OR","coords":["45.35734000","-122.60676000"]},{"commonName":"Orhei","countryCode":"MD","countryName":"Moldova","stateCode":"OR","coords":["47.38494000","28.82446000"]},{"commonName":"Ourense","countryCode":"ES","countryName":"Spain","stateCode":"OR","coords":["42.33669000","-7.86407000"]},{"commonName":"Pacific City","countryCode":"US","countryName":"United States","stateCode":"OR","coords":["45.20233000","-123.96289000"]},{"commonName":"Padampur","countryCode":"IN","countryName":"India","stateCode":"OR","coords":["20.99932000","83.06325000"]},{"commonName":"Paderne de Allariz","countryCode":"ES","countryName":"Spain","stateCode":"OR","coords":["42.27146620","-7.75094040"]},{"commonName":"Padrenda","countryCode":"ES","countryName":"Spain","stateCode":"OR","coords":["42.13333000","-8.15000000"]},{"commonName":"Parada de Sil","countryCode":"ES","countryName":"Spain","stateCode":"OR","coords":["42.38242790","-7.56772080"]},{"commonName":"Paradip Garh","countryCode":"IN","countryName":"India","stateCode":"OR","coords":["20.31641000","86.60850000"]},{"commonName":"Patamundai","countryCode":"IN","countryName":"India","stateCode":"OR","coords":["20.57806000","86.56063000"]},{"commonName":"Patnagarh","countryCode":"IN","countryName":"India","stateCode":"OR","coords":["20.70833000","83.13263000"]},{"commonName":"Pendleton","countryCode":"US","countryName":"United States","stateCode":"OR","coords":["45.67207000","-118.78860000"]},{"commonName":"Pereiro de Aguiar","countryCode":"ES","countryName":"Spain","stateCode":"OR","coords":["42.34524000","-7.80008000"]},{"commonName":"Pereiro de Aguiar O","countryCode":"ES","countryName":"Spain","stateCode":"OR","coords":["42.33578930","-7.86388100"]},{"commonName":"Peroxa A","countryCode":"ES","countryName":"Spain","stateCode":"OR","coords":["42.45231580","-7.79601180"]},{"commonName":"Petín","countryCode":"ES","countryName":"Spain","stateCode":"OR","coords":["42.38191000","-7.12899000"]},{"commonName":"Philomath","countryCode":"US","countryName":"United States","stateCode":"OR","coords":["44.54012000","-123.36760000"]},{"commonName":"Phoenix","countryCode":"US","countryName":"United States","stateCode":"OR","coords":["42.27541000","-122.81809000"]},{"commonName":"Phulbani","countryCode":"IN","countryName":"India","stateCode":"OR","coords":["20.48101000","84.23063000"]},{"commonName":"Pilot Rock","countryCode":"US","countryName":"United States","stateCode":"OR","coords":["45.48318000","-118.82998000"]},{"commonName":"Piñor","countryCode":"ES","countryName":"Spain","stateCode":"OR","coords":["42.50120000","-8.00151000"]},{"commonName":"Pipili","countryCode":"IN","countryName":"India","stateCode":"OR","coords":["20.11357000","85.83147000"]},{"commonName":"Pobra de Trives A","countryCode":"ES","countryName":"Spain","stateCode":"OR","coords":["42.33934680","-7.25380970"]},{"commonName":"Polasara","countryCode":"IN","countryName":"India","stateCode":"OR","coords":["19.69386000","84.81401000"]},{"commonName":"Polk County","countryCode":"US","countryName":"United States","stateCode":"OR","coords":["44.90348000","-123.41337000"]},{"commonName":"Pontedeva","countryCode":"ES","countryName":"Spain","stateCode":"OR","coords":["42.16561270","-8.13768240"]},{"commonName":"Porqueira","countryCode":"ES","countryName":"Spain","stateCode":"OR","coords":["42.01667000","-7.85000000"]},{"commonName":"Port Orford","countryCode":"US","countryName":"United States","stateCode":"OR","coords":["42.74566000","-124.49733000"]},{"commonName":"Portland","countryCode":"US","countryName":"United States","stateCode":"OR","coords":["45.52345000","-122.67621000"]},{"commonName":"Prineville","countryCode":"US","countryName":"United States","stateCode":"OR","coords":["44.29985000","-120.83447000"]},{"commonName":"Punxín","countryCode":"ES","countryName":"Spain","stateCode":"OR","coords":["42.37862830","-8.01379400"]},{"commonName":"Puri","countryCode":"IN","countryName":"India","stateCode":"OR","coords":["19.90000000","85.60000000"]},{"commonName":"Purushottampur","countryCode":"IN","countryName":"India","stateCode":"OR","coords":["19.52024000","84.88514000"]},{"commonName":"Quintela de Leirado","countryCode":"ES","countryName":"Spain","stateCode":"OR","coords":["42.13967000","-8.10126000"]},{"commonName":"Rainier","countryCode":"US","countryName":"United States","stateCode":"OR","coords":["46.08900000","-122.93594000"]},{"commonName":"Rairiz de Veiga","countryCode":"ES","countryName":"Spain","stateCode":"OR","coords":["42.08364000","-7.83503000"]},{"commonName":"Raleigh Hills","countryCode":"US","countryName":"United States","stateCode":"OR","coords":["45.48067000","-122.76204000"]},{"commonName":"Rambha","countryCode":"IN","countryName":"India","stateCode":"OR","coords":["19.51667000","85.10000000"]},{"commonName":"Ramirás","countryCode":"ES","countryName":"Spain","stateCode":"OR","coords":["42.28320310","-8.01928670"]},{"commonName":"Raurkela","countryCode":"IN","countryName":"India","stateCode":"OR","coords":["22.22496000","84.86414000"]},{"commonName":"Rayagada","countryCode":"IN","countryName":"India","stateCode":"OR","coords":["19.40000000","83.50000000"]},{"commonName":"Redmond","countryCode":"US","countryName":"United States","stateCode":"OR","coords":["44.27262000","-121.17392000"]},{"commonName":"Redwood","countryCode":"US","countryName":"United States","stateCode":"OR","coords":["42.42206000","-123.38728000"]},{"commonName":"Reedsport","countryCode":"US","countryName":"United States","stateCode":"OR","coords":["43.70234000","-124.09678000"]},{"commonName":"Remuna","countryCode":"IN","countryName":"India","stateCode":"OR","coords":["21.52798000","86.87156000"]},{"commonName":"Rengali","countryCode":"IN","countryName":"India","stateCode":"OR","coords":["21.64602000","84.05311000"]},{"commonName":"Ribadavia","countryCode":"ES","countryName":"Spain","stateCode":"OR","coords":["42.28804000","-8.14362000"]},{"commonName":"Riddle","countryCode":"US","countryName":"United States","stateCode":"OR","coords":["42.95095000","-123.36423000"]},{"commonName":"Riós","countryCode":"ES","countryName":"Spain","stateCode":"OR","coords":["41.97457000","-7.28234000"]},{"commonName":"Rockaway Beach","countryCode":"US","countryName":"United States","stateCode":"OR","coords":["45.61344000","-123.94291000"]},{"commonName":"Rockcreek","countryCode":"US","countryName":"United States","stateCode":"OR","coords":["45.55012000","-122.87705000"]},{"commonName":"Rogue River","countryCode":"US","countryName":"United States","stateCode":"OR","coords":["42.43595000","-123.17200000"]},{"commonName":"Rose Lodge","countryCode":"US","countryName":"United States","stateCode":"OR","coords":["45.01039000","-123.88039000"]},{"commonName":"Roseburg","countryCode":"US","countryName":"United States","stateCode":"OR","coords":["43.21650000","-123.34174000"]},{"commonName":"Roseburg North","countryCode":"US","countryName":"United States","stateCode":"OR","coords":["43.26452000","-123.30331000"]},{"commonName":"Rúa A","countryCode":"ES","countryName":"Spain","stateCode":"OR","coords":["42.33932800","-7.84871580"]},{"commonName":"Rubiá","countryCode":"ES","countryName":"Spain","stateCode":"OR","coords":["42.47145850","-6.88872020"]},{"commonName":"Saint Helens","countryCode":"US","countryName":"United States","stateCode":"OR","coords":["45.86400000","-122.80649000"]},{"commonName":"Salem","countryCode":"US","countryName":"United States","stateCode":"OR","coords":["44.94290000","-123.03510000"]},{"commonName":"Sambalpur","countryCode":"IN","countryName":"India","stateCode":"OR","coords":["21.40000000","83.88333000"]},{"commonName":"San Amaro","countryCode":"ES","countryName":"Spain","stateCode":"OR","coords":["42.37385000","-8.07347000"]},{"commonName":"San Cibrao das Viñas","countryCode":"ES","countryName":"Spain","stateCode":"OR","coords":["42.29484450","-7.87284030"]},{"commonName":"San Cristovo de Cea","countryCode":"ES","countryName":"Spain","stateCode":"OR","coords":["42.50038680","-7.94838980"]},{"commonName":"San Xoán de Río","countryCode":"ES","countryName":"Spain","stateCode":"OR","coords":["42.37059030","-7.29937170"]},{"commonName":"Sandiás","countryCode":"ES","countryName":"Spain","stateCode":"OR","coords":["42.10250340","-7.75253520"]},{"commonName":"Sandy","countryCode":"US","countryName":"United States","stateCode":"OR","coords":["45.39734000","-122.26148000"]},{"commonName":"Sarreaus","countryCode":"ES","countryName":"Spain","stateCode":"OR","coords":["42.08784000","-7.60348000"]},{"commonName":"Scappoose","countryCode":"US","countryName":"United States","stateCode":"OR","coords":["45.75428000","-122.87760000"]},{"commonName":"Seaside","countryCode":"US","countryName":"United States","stateCode":"OR","coords":["45.99316000","-123.92264000"]},{"commonName":"Sebeta","countryCode":"ET","countryName":"Ethiopia","stateCode":"OR","coords":["8.91667000","38.61667000"]},{"commonName":"Sendafa","countryCode":"ET","countryName":"Ethiopia","stateCode":"OR","coords":["9.15203000","39.02335000"]},{"commonName":"Shady Cove","countryCode":"US","countryName":"United States","stateCode":"OR","coords":["42.61068000","-122.81254000"]},{"commonName":"Shakiso","countryCode":"ET","countryName":"Ethiopia","stateCode":"OR","coords":["5.76494000","38.91006000"]},{"commonName":"Shambu","countryCode":"ET","countryName":"Ethiopia","stateCode":"OR","coords":["9.56667000","37.10000000"]},{"commonName":"Shashemenē","countryCode":"ET","countryName":"Ethiopia","stateCode":"OR","coords":["7.20000000","38.60000000"]},{"commonName":"Sheridan","countryCode":"US","countryName":"United States","stateCode":"OR","coords":["45.09928000","-123.39483000"]},{"commonName":"Sherman County","countryCode":"US","countryName":"United States","stateCode":"OR","coords":["45.40521000","-120.68932000"]},{"commonName":"Sherwood","countryCode":"US","countryName":"United States","stateCode":"OR","coords":["45.35651000","-122.84010000"]},{"commonName":"Siletz","countryCode":"US","countryName":"United States","stateCode":"OR","coords":["44.72178000","-123.92011000"]},{"commonName":"Silverton","countryCode":"US","countryName":"United States","stateCode":"OR","coords":["45.00512000","-122.78315000"]},{"commonName":"Sirre","countryCode":"ET","countryName":"Ethiopia","stateCode":"OR","coords":["8.31667000","39.48333000"]},{"commonName":"Sisters","countryCode":"US","countryName":"United States","stateCode":"OR","coords":["44.29095000","-121.54921000"]},{"commonName":"Sonepur","countryCode":"IN","countryName":"India","stateCode":"OR","coords":["20.83333000","83.91667000"]},{"commonName":"Sorada","countryCode":"IN","countryName":"India","stateCode":"OR","coords":["19.76082000","84.42997000"]},{"commonName":"Soro","countryCode":"IN","countryName":"India","stateCode":"OR","coords":["21.27851000","86.68833000"]},{"commonName":"South Lebanon","countryCode":"US","countryName":"United States","stateCode":"OR","coords":["44.50623000","-122.90314000"]},{"commonName":"Springfield","countryCode":"US","countryName":"United States","stateCode":"OR","coords":["44.04624000","-123.02203000"]},{"commonName":"Stafford","countryCode":"US","countryName":"United States","stateCode":"OR","coords":["45.35734000","-122.72259000"]},{"commonName":"Stanfield","countryCode":"US","countryName":"United States","stateCode":"OR","coords":["45.78041000","-119.21724000"]},{"commonName":"Stayton","countryCode":"US","countryName":"United States","stateCode":"OR","coords":["44.80068000","-122.79453000"]},{"commonName":"Subarnapur","countryCode":"IN","countryName":"India","stateCode":"OR","coords":["20.93154000","83.82486000"]},{"commonName":"Sublimity","countryCode":"US","countryName":"United States","stateCode":"OR","coords":["44.82957000","-122.79453000"]},{"commonName":"Sundargarh","countryCode":"IN","countryName":"India","stateCode":"OR","coords":["22.25000000","84.50000000"]},{"commonName":"Sunriver","countryCode":"US","countryName":"United States","stateCode":"OR","coords":["43.88401000","-121.43864000"]},{"commonName":"Sutherlin","countryCode":"US","countryName":"United States","stateCode":"OR","coords":["43.39012000","-123.31258000"]},{"commonName":"Sweet Home","countryCode":"US","countryName":"United States","stateCode":"OR","coords":["44.39762000","-122.73620000"]},{"commonName":"Taboadela","countryCode":"ES","countryName":"Spain","stateCode":"OR","coords":["42.24234000","-7.82719000"]},{"commonName":"Talcher","countryCode":"IN","countryName":"India","stateCode":"OR","coords":["20.94927000","85.23354000"]},{"commonName":"Talent","countryCode":"US","countryName":"United States","stateCode":"OR","coords":["42.24568000","-122.78865000"]},{"commonName":"Tangent","countryCode":"US","countryName":"United States","stateCode":"OR","coords":["44.54123000","-123.10815000"]},{"commonName":"Tarabha","countryCode":"IN","countryName":"India","stateCode":"OR","coords":["20.73252000","83.67443000"]},{"commonName":"Teixeira A","countryCode":"ES","countryName":"Spain","stateCode":"OR","coords":["42.33578930","-7.86388100"]},{"commonName":"Terrebonne","countryCode":"US","countryName":"United States","stateCode":"OR","coords":["44.35290000","-121.17781000"]},{"commonName":"The Dalles","countryCode":"US","countryName":"United States","stateCode":"OR","coords":["45.59456000","-121.17868000"]},{"commonName":"Three Rivers","countryCode":"US","countryName":"United States","stateCode":"OR","coords":["43.82012000","-121.46919000"]},{"commonName":"Tigard","countryCode":"US","countryName":"United States","stateCode":"OR","coords":["45.43123000","-122.77149000"]},{"commonName":"Tillamook","countryCode":"US","countryName":"United States","stateCode":"OR","coords":["45.45640000","-123.84553000"]},{"commonName":"Tillamook County","countryCode":"US","countryName":"United States","stateCode":"OR","coords":["45.45645000","-123.75877000"]},{"commonName":"Titlagarh","countryCode":"IN","countryName":"India","stateCode":"OR","coords":["20.28961000","83.15233000"]},{"commonName":"Toén","countryCode":"ES","countryName":"Spain","stateCode":"OR","coords":["42.31765000","-7.95435000"]},{"commonName":"Toledo","countryCode":"US","countryName":"United States","stateCode":"OR","coords":["44.62151000","-123.93845000"]},{"commonName":"Trasmiras","countryCode":"ES","countryName":"Spain","stateCode":"OR","coords":["42.02540000","-7.61735000"]},{"commonName":"Tri-City","countryCode":"US","countryName":"United States","stateCode":"OR","coords":["42.98456000","-123.31173000"]},{"commonName":"Troutdale","countryCode":"US","countryName":"United States","stateCode":"OR","coords":["45.53929000","-122.38731000"]},{"commonName":"Tualatin","countryCode":"US","countryName":"United States","stateCode":"OR","coords":["45.38401000","-122.76399000"]},{"commonName":"Tulu Bolo","countryCode":"ET","countryName":"Ethiopia","stateCode":"OR","coords":["8.66667000","38.21667000"]},{"commonName":"Turner","countryCode":"US","countryName":"United States","stateCode":"OR","coords":["44.84318000","-122.95287000"]},{"commonName":"Udayagiri","countryCode":"IN","countryName":"India","stateCode":"OR","coords":["20.12416000","84.36869000"]},{"commonName":"Umatilla","countryCode":"US","countryName":"United States","stateCode":"OR","coords":["45.91735000","-119.34252000"]},{"commonName":"Umatilla County","countryCode":"US","countryName":"United States","stateCode":"OR","coords":["45.59190000","-118.73683000"]},{"commonName":"Union","countryCode":"US","countryName":"United States","stateCode":"OR","coords":["45.20847000","-117.86521000"]},{"commonName":"Union County","countryCode":"US","countryName":"United States","stateCode":"OR","coords":["45.31035000","-118.00900000"]},{"commonName":"Vale","countryCode":"US","countryName":"United States","stateCode":"OR","coords":["43.98211000","-117.23823000"]},{"commonName":"Veiga A","countryCode":"ES","countryName":"Spain","stateCode":"OR","coords":["42.13776390","-7.92993400"]},{"commonName":"Veneta","countryCode":"US","countryName":"United States","stateCode":"OR","coords":["44.04873000","-123.35093000"]},{"commonName":"Verea","countryCode":"ES","countryName":"Spain","stateCode":"OR","coords":["42.10653000","-8.00092000"]},{"commonName":"Verín","countryCode":"ES","countryName":"Spain","stateCode":"OR","coords":["41.94149000","-7.43809000"]},{"commonName":"Vernonia","countryCode":"US","countryName":"United States","stateCode":"OR","coords":["45.85872000","-123.19289000"]},{"commonName":"Viana do Bolo","countryCode":"ES","countryName":"Spain","stateCode":"OR","coords":["42.33896300","-7.85202770"]},{"commonName":"Vilamarín","countryCode":"ES","countryName":"Spain","stateCode":"OR","coords":["42.46507870","-7.89018920"]},{"commonName":"Vilamartín de Valdeorras","countryCode":"ES","countryName":"Spain","stateCode":"OR","coords":["42.41339370","-7.05925530"]},{"commonName":"Vilar de Barrio","countryCode":"ES","countryName":"Spain","stateCode":"OR","coords":["42.15979160","-7.61277720"]},{"commonName":"Vilar de Santos","countryCode":"ES","countryName":"Spain","stateCode":"OR","coords":["42.08612310","-7.79465270"]},{"commonName":"Vilardevós","countryCode":"ES","countryName":"Spain","stateCode":"OR","coords":["41.90731400","-7.31255920"]},{"commonName":"Vilariño de Conso","countryCode":"ES","countryName":"Spain","stateCode":"OR","coords":["42.16605680","-7.18327240"]},{"commonName":"Waldport","countryCode":"US","countryName":"United States","stateCode":"OR","coords":["44.42679000","-124.06873000"]},{"commonName":"Waliso","countryCode":"ET","countryName":"Ethiopia","stateCode":"OR","coords":["8.53417000","37.96515000"]},{"commonName":"Wallowa County","countryCode":"US","countryName":"United States","stateCode":"OR","coords":["45.57983000","-117.18107000"]},{"commonName":"Warm Springs","countryCode":"US","countryName":"United States","stateCode":"OR","coords":["44.76345000","-121.26616000"]},{"commonName":"Warren","countryCode":"US","countryName":"United States","stateCode":"OR","coords":["45.81900000","-122.84899000"]},{"commonName":"Warrenton","countryCode":"US","countryName":"United States","stateCode":"OR","coords":["46.16510000","-123.92376000"]},{"commonName":"Wasco County","countryCode":"US","countryName":"United States","stateCode":"OR","coords":["45.16005000","-121.16815000"]},{"commonName":"Washington County","countryCode":"US","countryName":"United States","stateCode":"OR","coords":["45.56007000","-123.09849000"]},{"commonName":"Wenjī","countryCode":"ET","countryName":"Ethiopia","stateCode":"OR","coords":["8.45000000","39.28333000"]},{"commonName":"West Harerghe Zone","countryCode":"ET","countryName":"Ethiopia","stateCode":"OR","coords":["8.67245000","40.84885000"]},{"commonName":"West Haven","countryCode":"US","countryName":"United States","stateCode":"OR","coords":["45.51762000","-122.76954000"]},{"commonName":"West Haven-Sylvan","countryCode":"US","countryName":"United States","stateCode":"OR","coords":["45.51613000","-122.76809000"]},{"commonName":"West Linn","countryCode":"US","countryName":"United States","stateCode":"OR","coords":["45.36568000","-122.61231000"]},{"commonName":"West Slope","countryCode":"US","countryName":"United States","stateCode":"OR","coords":["45.49873000","-122.76454000"]},{"commonName":"West Wellega Zone","countryCode":"ET","countryName":"Ethiopia","stateCode":"OR","coords":["9.17283000","35.05279000"]},{"commonName":"Wheeler County","countryCode":"US","countryName":"United States","stateCode":"OR","coords":["44.72606000","-120.02746000"]},{"commonName":"White City","countryCode":"US","countryName":"United States","stateCode":"OR","coords":["42.43735000","-122.85893000"]},{"commonName":"Willamina","countryCode":"US","countryName":"United States","stateCode":"OR","coords":["45.07873000","-123.48594000"]},{"commonName":"Williams","countryCode":"US","countryName":"United States","stateCode":"OR","coords":["42.21873000","-123.27394000"]},{"commonName":"Wilsonville","countryCode":"US","countryName":"United States","stateCode":"OR","coords":["45.29984000","-122.77371000"]},{"commonName":"Winston","countryCode":"US","countryName":"United States","stateCode":"OR","coords":["43.12234000","-123.41257000"]},{"commonName":"Wood Village","countryCode":"US","countryName":"United States","stateCode":"OR","coords":["45.53429000","-122.41870000"]},{"commonName":"Woodburn","countryCode":"US","countryName":"United States","stateCode":"OR","coords":["45.14373000","-122.85537000"]},{"commonName":"Xinzo de Limia","countryCode":"ES","countryName":"Spain","stateCode":"OR","coords":["42.06350000","-7.72459000"]},{"commonName":"Xunqueira de Ambía","countryCode":"ES","countryName":"Spain","stateCode":"OR","coords":["42.20362720","-7.73691740"]},{"commonName":"Xunqueira de Espadanedo","countryCode":"ES","countryName":"Spain","stateCode":"OR","coords":["42.31837970","-7.62938430"]},{"commonName":"Yabēlo","countryCode":"ET","countryName":"Ethiopia","stateCode":"OR","coords":["4.88333000","38.08333000"]},{"commonName":"Yamhill","countryCode":"US","countryName":"United States","stateCode":"OR","coords":["45.34150000","-123.18733000"]},{"commonName":"Yamhill County","countryCode":"US","countryName":"United States","stateCode":"OR","coords":["45.23260000","-123.30815000"]},{"commonName":"Yoncalla","countryCode":"US","countryName":"United States","stateCode":"OR","coords":["43.59845000","-123.28342000"]},{"commonName":"Ziway","countryCode":"ET","countryName":"Ethiopia","stateCode":"OR","coords":["7.93333000","38.71667000"]}]